upyun/__init__.py
upyun/av.py
upyun/form.py
upyun/rest.py
upyun/resume.py
upyun/upyun.py
upyun/modules/__init__.py
upyun/modules/compat.py
upyun/modules/exception.py
upyun/modules/httpipe.py
upyun/modules/sign.py
upyun-2.5.3.dist-info/METADATA
upyun-2.5.3.dist-info/WHEEL
upyun-2.5.3.dist-info/top_level.txt
upyun-2.5.3.dist-info/RECORD
