Metadata-Version: 2.1
Name: upyun
Version: 2.5.3
Summary: UpYun Storage SDK for Python
Home-page: https://github.com/upyun/python-sdk
Author: Monkey Zhang (timebug)
Author-email: timebug.info@gmail.com
License: License :: OSI Approved :: MIT License
Keywords: upyun,python,sdk
Platform: Platform Independent
Classifier: Development Status :: 5 - Production/Stable
Classifier: Intended Audience :: Developers
Classifier: License :: OSI Approved :: MIT License
Classifier: Operating System :: OS Independent
Classifier: Programming Language :: Python
Classifier: Programming Language :: Python :: 2
Classifier: Programming Language :: Python :: 2.7
Classifier: Programming Language :: Python :: 3
Classifier: Programming Language :: Python :: 3.3
Classifier: Programming Language :: Python :: 3.4
Requires-Dist: requests (>=2.4.3)
